dash_swiper/DashCarousel.py
dash_swiper/DashSwiper.py
dash_swiper/__init__.py
dash_swiper/_imports_.py
dash_swiper/dash_swiper.min.js
dash_swiper/dash_swiper.min.js.map
dash_swiper/metadata.json
dash_swiper/package-info.json
dash_swiper-0.0.3.dist-info/LICENSE
dash_swiper-0.0.3.dist-info/METADATA
dash_swiper-0.0.3.dist-info/WHEEL
dash_swiper-0.0.3.dist-info/top_level.txt
dash_swiper-0.0.3.dist-info/RECORD
