Metadata-Version: 2.1
Name: dash_swiper
Version: 0.0.3
Summary: swiper for dash
Author: pip install python <pipinstallpython@gmail.com>
License: MIT
Classifier: Framework :: Dash
License-File: LICENSE
